{
  "version": "2.0.0",
  "strategy": "hybrid",
  "minified": false,
  "obfuscated": false,
  "production": true,
  "generated": "2026-04-04T18:21:00.100Z",
  "stats": {
    "totalComponents": 60,
    "totalRoutes": 7,
    "sharedComponents": 2,
    "sharedPercentage": "1.7",
    "totalSize": 2175620,
    "criticalSize": 38550
  },
  "bundles": {
    "framework": {
      "file": "slice-bundle.framework.js",
      "size": 0,
      "hash": null,
      "integrity": null,
      "components": []
    },
    "critical": {
      "file": "slice-bundle.critical.js",
      "size": 38550,
      "hash": "46fac169e88a5be06e23920c4ccd9b805769cf141e3289a143a2f205d5387b16",
      "integrity": "sha256:46fac169e88a5be06e23920c4ccd9b805769cf141e3289a143a2f205d5387b16",
      "components": [
        "Loading",
        "Layout"
      ]
    },
    "routes": {
      "multiroute-Portfolio": {
        "path": [
          "/",
          "/experience",
          "/education",
          "/slice-js",
          "/projects"
        ],
        "file": "slice-bundle.multiroute-portfolio.js",
        "size": 1795924,
        "hash": "683a8ee9f8f15c2ef25f6afe770c4ecb5660af74497a989fdd7c38d8624a23e8",
        "integrity": "sha256:683a8ee9f8f15c2ef25f6afe770c4ecb5660af74497a989fdd7c38d8624a23e8",
        "components": [
          "Portfolio",
          "ThemeSelector",
          "Navbar",
          "Link",
          "DropDown",
          "Button",
          "Icon",
          "MultiRoute",
          "AboutSection",
          "Grid",
          "Card",
          "TechExpertise",
          "BadgeCarousel",
          "ImageCarrousel",
          "RandomFacts",
          "ExperienceSection",
          "Timeline",
          "ExperienceCard",
          "Tabs",
          "EducationSection",
          "StudyCard",
          "CertificateCard",
          "WhatIsSlice",
          "ProjectsSection",
          "ProjectViewer",
          "BuiltWithBadge"
        ],
        "dependencies": [
          "critical"
        ]
      },
      "general": {
        "path": [
          "/imposter"
        ],
        "file": "slice-bundle.general.js",
        "size": 1637559,
        "hash": "597efeb51f15b055892b7bdc5a5435e8a06b89a7eda5bdf46d36c012df5aabb2",
        "integrity": "sha256:597efeb51f15b055892b7bdc5a5435e8a06b89a7eda5bdf46d36c012df5aabb2",
        "components": [
          "TheImposterGame",
          "ImposterGameContextService",
          "ConfirmationModal",
          "Button",
          "Icon",
          "ThemeSelector",
          "BackgroundAudioToggle",
          "ClickSoundToggle",
          "GameSetup",
          "LocalStorageManager",
          "Select",
          "Input",
          "CategoryManagerModal",
          "NameManagerModal",
          "WordReveal",
          "GameFlow"
        ],
        "dependencies": [
          "critical"
        ]
      },
      "misc": {
        "path": [
          "/404"
        ],
        "file": "slice-bundle.misc.js",
        "size": 5289,
        "hash": "3c66e9f383a42cfe7aa860ab59108bde19e0511bd74af6361c6c22f139a42e7c",
        "integrity": "sha256:3c66e9f383a42cfe7aa860ab59108bde19e0511bd74af6361c6c22f139a42e7c",
        "components": [
          "NotFound"
        ],
        "dependencies": [
          "critical"
        ]
      }
    }
  },
  "routeBundles": {
    "/": [
      "critical",
      "multiroute-Portfolio"
    ],
    "/experience": [
      "critical",
      "multiroute-Portfolio"
    ],
    "/education": [
      "critical",
      "multiroute-Portfolio"
    ],
    "/slice-js": [
      "critical",
      "multiroute-Portfolio"
    ],
    "/projects": [
      "critical",
      "multiroute-Portfolio"
    ],
    "/imposter": [
      "critical",
      "general"
    ],
    "/404": [
      "critical",
      "misc"
    ]
  }
}
